webthing_ws/__init__.py
webthing_ws/exceptions.py
webthing_ws-0.1.1.dist-info/LICENSE
webthing_ws-0.1.1.dist-info/METADATA
webthing_ws-0.1.1.dist-info/WHEEL
webthing_ws-0.1.1.dist-info/top_level.txt
webthing_ws-0.1.1.dist-info/zip-safe
webthing_ws-0.1.1.dist-info/RECORD
