Metadata-Version: 2.1
Name: webthing-ws
Version: 0.1.1
Summary: A WebThing WebSocket consumer and API client.
Home-page: https://github.com/home-assistant-ecosystem/webthing-ws
Author: Fabian Affolter
Author-email: fabian@affolter-engineering.ch
License: MIT
Download-URL: https://github.com/home-assistant-ecosystem/webthing-ws/releases
Platform: UNKNOWN
Classifier: Development Status :: 3 - Alpha
Classifier: Environment :: Console
Classifier: Intended Audience :: Developers
Classifier: License :: OSI Approved :: MIT License
Classifier: Operating System :: MacOS :: MacOS X
Classifier: Operating System :: Microsoft :: Windows
Classifier: Operating System :: POSIX
Classifier: Programming Language :: Python :: 3.7
Classifier: Programming Language :: Python :: 3.8
Classifier: Topic :: Utilities
Requires-Dist: aiohttp (<4,>=3.7.4)
Requires-Dist: async-timeout (<4)
